{
  "entityType" : "NOTIFICATION_RULE",
  "entity" : {
    "additionalConfig" : {
      "description" : "Send notification to tenant admins when any Rule chain or Rule node failed to start, update or stop"
    },
    "enabled" : true,
    "externalId" : {
      "entityType" : "NOTIFICATION_RULE",
      "id" : "2c2086b0-03d2-11f0-b49e-73e9f982809f"
    },
    "id" : {
      "entityType" : "NOTIFICATION_RULE",
      "id" : "2c2086b0-03d2-11f0-b49e-73e9f982809f"
    },
    "name" : "Rule node initialization failure",
    "recipientsConfig" : {
      "targets" : [ "2c10a830-03d2-11f0-b49e-73e9f982809f" ],
      "triggerType" : "RULE_ENGINE_COMPONENT_LIFECYCLE_EVENT"
    },
    "templateId" : {
      "entityType" : "NOTIFICATION_TEMPLATE",
      "id" : "2c1f9c50-03d2-11f0-b49e-73e9f982809f"
    },
    "triggerConfig" : {
      "triggerType" : "RULE_ENGINE_COMPONENT_LIFECYCLE_EVENT",
      "onlyRuleChainLifecycleFailures" : true,
      "onlyRuleNodeLifecycleFailures" : true,
      "ruleChainEvents" : [ "STARTED", "UPDATED", "STOPPED" ],
      "ruleChains" : null,
      "ruleNodeEvents" : [ "STARTED", "UPDATED", "STOPPED" ],
      "trackRuleNodeEvents" : true,
      "triggerType" : "RULE_ENGINE_COMPONENT_LIFECYCLE_EVENT"
    },
    "triggerType" : "RULE_ENGINE_COMPONENT_LIFECYCLE_EVENT"
  }
}